mattSorts/__init__.py
mattSorts-0.1.dist-info/LICENSE.txt
mattSorts-0.1.dist-info/METADATA
mattSorts-0.1.dist-info/WHEEL
mattSorts-0.1.dist-info/top_level.txt
mattSorts-0.1.dist-info/RECORD
