Metadata-Version: 2.1
Name: mattSorts
Version: 0.1
Summary: A sorts example package
Home-page: https://github.com/tablescraper-selected-row/mattSorts
Author: benjaminnn
Author-email: smatthew.gasparetti@itis.pr.it
Classifier: Development Status :: 3 - Alpha
Classifier: Intended Audience :: Developers
Classifier: License :: OSI Approved :: MIT License
Classifier: Programming Language :: Python :: 3
Classifier: Programming Language :: Python :: 3.6
Classifier: Programming Language :: Python :: 3.7
Classifier: Programming Language :: Python :: 3.8
License-File: LICENSE.txt
